bpsgeodb/__init__.py
bpsgeodb/bpsgeodb.py
bpsgeodb/version.py
bpsgeodb-0.0.5.dist-info/LICENSE
bpsgeodb-0.0.5.dist-info/METADATA
bpsgeodb-0.0.5.dist-info/WHEEL
bpsgeodb-0.0.5.dist-info/top_level.txt
bpsgeodb-0.0.5.dist-info/RECORD
