Metadata-Version: 2.1
Name: bpsgeodb
Version: 0.0.5
Summary: BPS Geodatabase - API Authorization and Access Python Modules
Home-page: https://github.com/brazil-petrostudies/python-bpsgeodb
Author: Brazil Petrostudies Servicos Geologicos Ltda
Author-email: support@brazilpetrostudies.com.br
License: UNKNOWN
Platform: UNKNOWN
Classifier: Programming Language :: Python :: 3
Classifier: License :: OSI Approved :: MIT License
Classifier: Operating System :: OS Independent
Requires-Python: >=3.6
